{
  "usuarios": [
    {
      "nome": "Luiz Otávio",
      "senha": "123",
      "email": "luizindocapa@gmail.com",
      "permissao": "1",
      "dataCriacao": "26/06/2023",
      "telefone": "31988888888",
      "trabalhos": "0",
      "imagem_perfil": "",
      "id": 1
    },
    {
      "nome": "Michael Fernades",
      "senha": "123",
      "email": "mich123@gmail.com",
      "permissao": "2",
      "dataCriacao": "26/06/2023",
      "telefone": "31988883120",
      "trabalhos": "0",
      "imagem_perfil": "../Img/barbeiro1.png",
      "id": 2
    },
    {
      "nome": "Samuel Nogueira",
      "senha": "123",
      "email": "user3@gmail.com",
      "permissao": "3",
      "dataCriacao": "26/06/2023",
      "telefone": "31988884032",
      "trabalhos": "0",
      "imagem_perfil": "../Img/barbeiro2.png",
      "id": 3
    },
    {
      "nome": "Romario",
      "senha": "123",
      "email": "romario@gmail.com",
      "permissao": "1",
      "dataCriacao": "26/06/2023",
      "telefone": "31988882380",
      "trabalhos": "0",
      "imagem_perfil": "",
      "id": 4
    },
    {
      "nome": "Washington Dias",
      "senha": "123",
      "email": "washington@gmail.com",
      "permissao": "2",
      "dataCriacao": "26/06/2023",
      "telefone": "31988490372",
      "trabalhos": "0",
      "imagem_perfil": "../Img/barbeiro3.png",
      "id": 5
    },
    {
      "nome": "Felipe Melo",
      "senha": "123",
      "email": "user3@gmail.com",
      "permissao": "2",
      "dataCriacao": "26/06/2023",
      "telefone": "31988889328",
      "trabalhos": "0",
      "imagem_perfil": "",
      "id": 6
    },
    {
      "nome": "Guilherme Simao Primeiro",
      "senha": "simao11",
      "email": "guisimao1@gmail.com",
      "permissao": "1",
      "dataCriacao": "27/06/2023",
      "telefone": "31 999998888",
      "trabalhos": "0",
      "imagem_perfil": "",
      "id": 7
    }
  ],
  "agendamentos": [
    {
      "data": "26/06/2023",
      "horario": "18:00",
      "cliente": "4",
      "barbeiro": "2",
      "servico": "Corte",
      "descricao": "Descrição teste",
      "status": "2",
      "id": 1
    },
    {
      "data": "28/06/2023",
      "horario": "18:00",
      "cliente": "4",
      "barbeiro": "5",
      "servico": "Corte",
      "descricao": "Descrição teste",
      "status": "1",
      "id": 2
    },
    {
      "data": "30/06/2023",
      "horario": "18:00",
      "cliente": "4",
      "barbeiro": "5",
      "servico": "Corte",
      "descricao": "Descrição teste",
      "status": "2",
      "id": 3
    },
    {
      "data": "04/07/2023",
      "horario": "18:00",
      "cliente": "1",
      "barbeiro": "3",
      "servico": "Corte",
      "descricao": "Descrição teste",
      "status": "2",
      "id": 4
    },
    {
      "data": "07/07/2023",
      "horario": "18:00",
      "cliente": "1",
      "barbeiro": "5",
      "servico": "Corte",
      "descricao": "Descrição teste",
      "status": "1",
      "id": 5
    },
    {
      "data": "26/06/2023",
      "horario": "18:00",
      "cliente": "4",
      "barbeiro": "5",
      "servico": "Corte",
      "descricao": "Descrição teste",
      "status": "3",
      "id": 6
    },
    {
      "data": "01/08/2023",
      "horario": "18:00",
      "cliente": "1",
      "barbeiro": "2",
      "servico": "Corte",
      "descricao": "Descrição teste",
      "status": "4",
      "id": 7
    },
    {
      "data": "05/19/2023",
      "horario": "10:00",
      "profissional": "William",
      "servico": "Barba",
      "descricao": "",
      "id": 8
    },
    {
      "data": "05/19/2023",
      "horario": "10:00",
      "profissional": "Samuel",
      "servico": "Corte",
      "descricao": "",
      "id": 9
    },
    {
      "data": "08/06/2023",
      "horario": "09:45",
      "profissional": "2",
      "servico": "Corte",
      "descricao": "",
      "id": 10
    },
    {
      "data": "16/06/2023",
      "horario": "09:45",
      "profissional": "2",
      "servico": "Relaxamento",
      "descricao": "",
      "id": 11
    },
    {
      "data": "30/06/2023",
      "horario": "09:45",
      "profissional": "2",
      "servico": "Corte",
      "descricao": "",
      "id": 12
    },
    {
      "data": "30/06/2023",
      "horario": "09:45",
      "profissional": "2",
      "servico": "Barba",
      "descricao": "",
      "id": 13
    },
    {
      "data": "30/06/2023",
      "horario": "08:30",
      "profissional": "2",
      "servico": "Relaxamento",
      "descricao": "",
      "id": 14
    },
    {
      "data": "11/06/2023",
      "horario": "08:30",
      "profissional": "2",
      "servico": "Barba",
      "descricao": "",
      "id": 15
    },
    {
      "data": "30/06/2023",
      "horario": "09:45",
      "profissional": "2",
      "servico": "Relaxamento",
      "descricao": "",
      "id": 16
    },
    {
      "data": "30/06/2023",
      "horario": "09:45",
      "profissional": "2",
      "servico": "Relaxamento",
      "descricao": "",
      "id": 17
    },
    {
      "data": "17/06/2023",
      "horario": "09:45",
      "profissional": "2",
      "servico": "Barba",
      "descricao": "",
      "id": 18
    },
    {
      "data": "30/06/2023",
      "horario": "08:30",
      "profissional": "2",
      "servico": "Corte",
      "descricao": "",
      "id": 19
    },
    {
      "data": "23/06/2023",
      "horario": "15:30",
      "profissional": "2",
      "servico": "Relaxamento",
      "descricao": "",
      "id": 20
    },
    {
      "data": "30/06/2023",
      "horario": "15:30",
      "profissional": "2",
      "servico": "Corte",
      "descricao": "",
      "id": 21
    },
    {
      "data": "24/06/2023",
      "horario": "15:30",
      "profissional": "2",
      "servico": "Relaxamento",
      "descricao": "",
      "id": 22
    },
    {
      "data": "30/06/2023",
      "horario": "10:00",
      "profissional": "2",
      "servico": "Corte",
      "descricao": "",
      "id": 23
    },
    {
      "data": "21/06/2023",
      "horario": "08:00",
      "cliente": 1,
      "profissional": "2",
      "servico": "Barba",
      "descricao": "",
      "id": 24
    },
    {
      "data": "21/06/2023",
      "horario": "15:45",
      "cliente": 1,
      "profissional": "2",
      "servico": "Barba",
      "descricao": "",
      "id": 25
    },
    {
      "data": "30/06/2023",
      "horario": "17:00",
      "cliente": 1,
      "profissional": "2",
      "servico": "Barba",
      "descricao": "",
      "id": 26
    },
    {
      "data": "30/06/2023",
      "horario": "21:00",
      "cliente": 1,
      "profissional": "2",
      "servico": "Teste",
      "descricao": "",
      "id": 27
    },
    {
      "data": "15/06/2023",
      "horario": "15:00",
      "cliente": 1,
      "profissional": "2",
      "servico": "Barba",
      "descricao": "",
      "id": 28
    },
    {
      "data": "30/06/2023",
      "horario": "15:00",
      "cliente": 1,
      "profissional": "2",
      "servico": "Barba",
      "descricao": "",
      "id": 29
    },
    {
      "data": "30/06/2023",
      "horario": "15:00",
      "cliente": {
        "nome": "Usuario3",
        "senha": "123",
        "email": "user3@gmail.com",
        "permissao": "3",
        "dataCriacao": "26/06/2023",
        "telefone": "31988888888",
        "trabalhos": "0",
        "imagem_perfil": "",
        "id": 3
      },
      "profissional": "2",
      "servico": "Barba",
      "descricao": "",
      "id": 30
    },
    {
      "data": "30/06/2023",
      "horario": "10:00",
      "cliente": {
        "nome": "Samuel Nogueira",
        "senha": "123",
        "email": "user3@gmail.com",
        "permissao": "3",
        "dataCriacao": "26/06/2023",
        "telefone": "31988884032",
        "trabalhos": "0",
        "imagem_perfil": "../Img/barbeiro2.png",
        "id": 3
      },
      "barbeiro": "2",
      "servico": "Relaxamento",
      "descricao": "",
      "id": 31
    },
    {
      "data": "23/06/2023",
      "horario": "10:00",
      "cliente": {
        "nome": "Samuel Nogueira",
        "senha": "123",
        "email": "user3@gmail.com",
        "permissao": "3",
        "dataCriacao": "26/06/2023",
        "telefone": "31988884032",
        "trabalhos": "0",
        "imagem_perfil": "../Img/barbeiro2.png",
        "id": 3
      },
      "barbeiro": "2",
      "servico": "Corte",
      "descricao": "",
      "id": 32
    },
    {
      "data": "23/06/2023",
      "horario": "11:00",
      "cliente": {
        "nome": "Samuel Nogueira",
        "senha": "123",
        "email": "user3@gmail.com",
        "permissao": "3",
        "dataCriacao": "26/06/2023",
        "telefone": "31988884032",
        "trabalhos": "0",
        "imagem_perfil": "../Img/barbeiro2.png",
        "id": 3
      },
      "barbeiro": "2",
      "servico": "Relaxamento",
      "descricao": "",
      "id": 33
    },
    {
      "data": "16/06/2023",
      "horario": "10:00",
      "cliente": {
        "nome": "Samuel Nogueira",
        "senha": "123",
        "email": "user3@gmail.com",
        "permissao": "3",
        "dataCriacao": "26/06/2023",
        "telefone": "31988884032",
        "trabalhos": "0",
        "imagem_perfil": "../Img/barbeiro2.png",
        "id": 3
      },
      "barbeiro": "2",
      "servico": "Corte",
      "descricao": "",
      "id": 34
    },
    {
      "data": "08/06/2023",
      "horario": "14:00",
      "cliente": {
        "nome": "Samuel Nogueira",
        "senha": "123",
        "email": "user3@gmail.com",
        "permissao": "3",
        "dataCriacao": "26/06/2023",
        "telefone": "31988884032",
        "trabalhos": "0",
        "imagem_perfil": "../Img/barbeiro2.png",
        "id": 3
      },
      "barbeiro": "2",
      "servico": "Teste",
      "descricao": "",
      "id": 35
    },
    {
      "data": "23/06/2023",
      "horario": "14:00",
      "cliente": {
        "nome": "Samuel Nogueira",
        "senha": "123",
        "email": "user3@gmail.com",
        "permissao": "3",
        "dataCriacao": "26/06/2023",
        "telefone": "31988884032",
        "trabalhos": "0",
        "imagem_perfil": "../Img/barbeiro2.png",
        "id": 3
      },
      "barbeiro": "2",
      "servico": "Barba",
      "descricao": "",
      "id": 36
    },
    {
      "data": "30/06/2023",
      "horario": "11:00",
      "cliente": {
        "nome": "Samuel Nogueira",
        "senha": "123",
        "email": "user3@gmail.com",
        "permissao": "3",
        "dataCriacao": "26/06/2023",
        "telefone": "31988884032",
        "trabalhos": "0",
        "imagem_perfil": "../Img/barbeiro2.png",
        "id": 3
      },
      "barbeiro": "2",
      "servico": "Relaxamento",
      "descricao": "",
      "id": 37
    },
    {
      "data": "15/06/2023",
      "horario": "10:00",
      "cliente": {
        "nome": "Samuel Nogueira",
        "senha": "123",
        "email": "user3@gmail.com",
        "permissao": "3",
        "dataCriacao": "26/06/2023",
        "telefone": "31988884032",
        "trabalhos": "0",
        "imagem_perfil": "../Img/barbeiro2.png",
        "id": 3
      },
      "barbeiro": "2",
      "servico": "Relaxamento",
      "descricao": "",
      "id": 38
    },
    {
      "data": "08/06/2023",
      "horario": "14:00",
      "cliente": {
        "nome": "Samuel Nogueira",
        "senha": "123",
        "email": "user3@gmail.com",
        "permissao": "3",
        "dataCriacao": "26/06/2023",
        "telefone": "31988884032",
        "trabalhos": "0",
        "imagem_perfil": "../Img/barbeiro2.png",
        "id": 3
      },
      "barbeiro": "5",
      "servico": "Barba",
      "descricao": "",
      "id": 39
    },
    {
      "data": "23/06/2023",
      "horario": "15:00",
      "cliente": {
        "nome": "Samuel Nogueira",
        "senha": "123",
        "email": "user3@gmail.com",
        "permissao": "3",
        "dataCriacao": "26/06/2023",
        "telefone": "31988884032",
        "trabalhos": "0",
        "imagem_perfil": "../Img/barbeiro2.png",
        "id": 3
      },
      "barbeiro": "2",
      "servico": "Barba",
      "descricao": "",
      "id": 40
    },
    {
      "data": "08/06/2023",
      "horario": "11:00",
      "cliente": {
        "nome": "Samuel Nogueira",
        "senha": "123",
        "email": "user3@gmail.com",
        "permissao": "3",
        "dataCriacao": "26/06/2023",
        "telefone": "31988884032",
        "trabalhos": "0",
        "imagem_perfil": "../Img/barbeiro2.png",
        "id": 3
      },
      "barbeiro": "2",
      "servico": "Barba",
      "descricao": "",
      "id": 41
    },
    {
      "data": "15/06/2023",
      "horario": "11:00",
      "cliente": {
        "nome": "Samuel Nogueira",
        "senha": "123",
        "email": "user3@gmail.com",
        "permissao": "3",
        "dataCriacao": "26/06/2023",
        "telefone": "31988884032",
        "trabalhos": "0",
        "imagem_perfil": "../Img/barbeiro2.png",
        "id": 3
      },
      "barbeiro": "2",
      "servico": "Corte",
      "descricao": "",
      "id": 42
    },
    {
      "data": "30/06/2023",
      "horario": "09:00",
      "cliente": {
        "nome": "Samuel Nogueira",
        "senha": "123",
        "email": "user3@gmail.com",
        "permissao": "3",
        "dataCriacao": "26/06/2023",
        "telefone": "31988884032",
        "trabalhos": "0",
        "imagem_perfil": "../Img/barbeiro2.png",
        "id": 3
      },
      "barbeiro": "2",
      "servico": "Barba",
      "descricao": "",
      "id": 43
    },
    {
      "data": "30/06/2023",
      "horario": "10:00",
      "cliente": {
        "nome": "Samuel Nogueira",
        "senha": "123",
        "email": "user3@gmail.com",
        "permissao": "3",
        "dataCriacao": "26/06/2023",
        "telefone": "31988884032",
        "trabalhos": "0",
        "imagem_perfil": "../Img/barbeiro2.png",
        "id": 3
      },
      "barbeiro": "5",
      "servico": "Relaxamento",
      "descricao": "",
      "id": 44
    },
    {
      "data": "30/06/2023",
      "horario": "15:00",
      "cliente": {
        "nome": "Samuel Nogueira",
        "senha": "123",
        "email": "user3@gmail.com",
        "permissao": "3",
        "dataCriacao": "26/06/2023",
        "telefone": "31988884032",
        "trabalhos": "0",
        "imagem_perfil": "../Img/barbeiro2.png",
        "id": 3
      },
      "barbeiro": "5",
      "servico": "Corte",
      "descricao": "",
      "id": 45
    }
  ]
}